{"slotScene":"81_CupidsLoveWheel","slotID":"cupidslovewheel","slotName":"Bank of Wealth","isGaugeStackSlot":false,"use":{"useDev":true,"useQA":true,"useLive":true},"resource":{"bannerPrefab":"simpleImg","smallBannerImage":"80_081_CupidsLoveWheel","longBannerImage":"80_081_CupidsLoveWheel_10"},"loading":{"leftSymbolImage":"70_81_CupidsLoveWheel_1","leftSymbolTitle":"RAPID HIT JACKPOT","leftSymbolDescription":"4 STACKED WILD SYMBOLS.","rightSymbolImage":"70_81_CupidsLoveWheel_2","rightSymbolTitle":"CLASSIC FEATURE","rightSymbolDescription":"3 OR MORE TRIGGER\nFREE SPIN MODE."}}