{"slotScene":"101_CashShowdownClassic","slotID":"cashshowdownclassic","slotName":"Cash showdown Classic","isGaugeStackSlot":false,"use":{"useDev":true,"useQA":true,"useLive":true},"resource":{"bannerPrefab":"simpleImg","smallBannerImage":"80_101_CashShowdownClassic","longBannerImage":"80_101_CashShowdownClassic_10"},"loading":{"leftSymbolImage":"70_101_CashShowdownClassic_1","leftSymbolTitle":"SHOW DOWN","leftSymbolDescription":"RESPIN","rightSymbolImage":"70_101_CashShowdownClassic_2","rightSymbolTitle":"REMATCH","rightSymbolDescription":"RESPIN"}}