{"slotScene":"114_BunnyBank","slotID":"bunnybank","slotName":"Bunny Bank","isGaugeStackSlot":false,"use":{"useDev":true,"useQA":true,"useLive":true},"resource":{"bannerPrefab":"simpleImg","smallBannerImage":"80_114_BunnyBank","longBannerImage":"80_114_BunnyBank_10"},"loading":{"leftSymbolImage":"70_114_BunnyBank_1","leftSymbolTitle":"FREE SPINS","leftSymbolDescription":"3 OR MORE TRIGGER\nFREE SPIN MODE.","rightSymbolImage":"70_114_BunnyBank_2","rightSymbolTitle":"JACKPOT","rightSymbolDescription":"AWARDED WHEN 15 EGG\nAPPEAR ON REELS."}}