{"slotScene":"174_SuperSevenBlasts","slotID":"supersevenblasts","slotName":"Super Seven Blasts","isGaugeStackSlot":false,"use":{"useDev":true,"useQA":true,"useLive":true},"resource":{"bannerPrefab":"simpleImg","smallBannerImage":"80_174_SuperSevenBlasts","longBannerImage":"80_174_SuperSevenBlasts_10"},"loading":{"leftSymbolImage":"70_174_SuperSevenBlasts_1","leftSymbolTitle":"JACKPOT SCATTER","leftSymbolDescription":"3 OR MORE TRIGGER\nRESPIN MODE.","rightSymbolImage":"70_174_SuperSevenBlasts_2","rightSymbolTitle":"BONUS SYMBOL","rightSymbolDescription":"RANDOMLY UPGRADES\n7 OR 77 SYMBOL."}}