{"slotScene":"185_PawsomePanda","slotID":"pawsomepanda","slotName":"Pawsome Panda","isGaugeStackSlot":false,"use":{"useDev":true,"useQA":true,"useLive":true},"resource":{"bannerPrefab":"simpleImg","smallBannerImage":"80_185_PawsomePanda","longBannerImage":"80_185_PawsomePanda_10"},"loading":{"leftSymbolImage":"70_185_PawsomePanda_1","leftSymbolTitle":"SCATTER","leftSymbolDescription":"3 TRIGGERS LOCK & ROLL PILES.","rightSymbolImage":"70_185_PawsomePanda_2","rightSymbolTitle":"BONUS","rightSymbolDescription":"UNLOCKS THE UPPER ROW\nIN LOCK & ROLL PILES."}}